lyzr_python_sdk/README.md
lyzr_python_sdk/__init__.py
lyzr_python_sdk/base.py
lyzr_python_sdk/clients/__init__.py
lyzr_python_sdk/clients/agent.py
lyzr_python_sdk/clients/inference.py
lyzr_python_sdk/clients/providers.py
lyzr_python_sdk/clients/tools.py
lyzr_python_sdk/clients/workflow.py
lyzr_python_sdk/examples/example1.py
lyzr_python_sdk-0.1.5.dist-info/licenses/LICENSE
lyzr_python_sdk-0.1.5.dist-info/METADATA
lyzr_python_sdk-0.1.5.dist-info/WHEEL
lyzr_python_sdk-0.1.5.dist-info/top_level.txt
lyzr_python_sdk-0.1.5.dist-info/RECORD
