Metadata-Version: 2.4
Name: lyzr-python-sdk
Version: 0.1.5
Summary: A Python client library for interacting with the Lyzr Agent API
Home-page: https://github.com/LyzrCore/lyzr-python
Author: Lyzr
Author-email: Lyzr <support@lyzr.ai>
Maintainer-email: Lyzr <support@lyzr.ai>
License-Expression: MIT
Project-URL: Homepage, https://github.com/LyzrCore/lyzr-python
Project-URL: Documentation, https://docs.lyzr.ai
Project-URL: Repository, https://github.com/LyzrCore/lyzr-python
Project-URL: Bug Reports, https://github.com/LyzrCore/lyzr-python/issues
Keywords: lyzr,agent,api,client,llm,artificial intelligence
Classifier: Development Status :: 3 - Alpha
Classifier: Intended Audience :: Developers
Classifier: Operating System :: OS Independent
Classifier: Programming Language :: Python :: 3
Classifier: Programming Language :: Python :: 3.7
Classifier: Programming Language :: Python :: 3.8
Classifier: Programming Language :: Python :: 3.9
Classifier: Programming Language :: Python :: 3.10
Classifier: Programming Language :: Python :: 3.11
Classifier: Programming Language :: Python :: 3.12
Classifier: Topic :: Software Development :: Libraries :: Python Modules
Classifier: Topic :: Internet :: WWW/HTTP :: Dynamic Content
Classifier: Topic :: Scientific/Engineering :: Artificial Intelligence
Requires-Python: >=3.7
License-File: LICENSE
Requires-Dist: requests>=2.25.0
Provides-Extra: dev
Requires-Dist: pytest>=6.0; extra == "dev"
Requires-Dist: pytest-cov>=2.0; extra == "dev"
Requires-Dist: black>=21.0; extra == "dev"
Requires-Dist: flake8>=3.8; extra == "dev"
Requires-Dist: mypy>=0.800; extra == "dev"
Provides-Extra: docs
Requires-Dist: sphinx>=4.0; extra == "docs"
Requires-Dist: sphinx-rtd-theme>=1.0; extra == "docs"
Dynamic: author
Dynamic: home-page
Dynamic: license-file
Dynamic: requires-python
